cprintf/__init__.py
cprintf/color_print.py
cprintf-0.0.11.dist-info/METADATA
cprintf-0.0.11.dist-info/WHEEL
cprintf-0.0.11.dist-info/top_level.txt
cprintf-0.0.11.dist-info/RECORD
