Metadata-Version: 2.2
Name: cprintf
Version: 0.0.11
Summary: Printing and debugging with color
Home-page: https://github.com/wang-zhibo/cprintf
Author: gm.zhibo.wang
Author-email: gm.zhibo.wang@gmail.com
Classifier: Programming Language :: Python :: 3
Classifier: Operating System :: OS Independent
Requires-Python: >=3.6
Dynamic: author
Dynamic: author-email
Dynamic: classifier
Dynamic: description
Dynamic: description-content-type
Dynamic: home-page
Dynamic: requires-python
Dynamic: summary
